mediqbox/act/__init__.py
mediqbox/act/act.py
mediqbox/act/helpers.py
mediqbox_act-0.0.3.dist-info/METADATA
mediqbox_act-0.0.3.dist-info/WHEEL
mediqbox_act-0.0.3.dist-info/top_level.txt
mediqbox_act-0.0.3.dist-info/RECORD
