Metadata-Version: 2.1
Name: mediqbox-act
Version: 0.0.3
Summary: A mediqbox component for translating texts and files
Requires-Dist: mediqbox-download
Requires-Dist: requests-toolbelt
